CHANGES.rst
README.rst
releaser/__init__.py
releaser/git_steps.py
releaser/regex.py
releaser/steps.py
releaser-3.0.0.dist-info/LICENSE.rst
releaser-3.0.0.dist-info/WHEEL
releaser-3.0.0.dist-info/METADATA
releaser-3.0.0.dist-info/RECORD
